sc_gz_dashboard/__init__.py
sc_gz_dashboard/exceptions.py
sc_gz_dashboard/main.py
sc_gz_dashboard/utils.py
sc_gz_dashboard/configs/__init__.py
sc_gz_dashboard/configs/default.py
sc_gz_dashboard/db/__init__.py
sc_gz_dashboard/db/common_db_module.py
sc_gz_dashboard/db/common_sql.py
sc_gz_dashboard/flask/__init__.py
sc_gz_dashboard/flask/data/__init__.py
sc_gz_dashboard/flask/data/v1_0_0/__init__.py
sc_gz_dashboard/flask/data/v1_0_0/dashboard_data_view.py
sc_gz_dashboard/flask/data/v1_0_0/get_available_years.py
sc_gz_dashboard/flask/data/v1_0_0/get_dashboard_data.py
sc_gz_dashboard/flask/data/v1_0_0/get_year_report_time.py
sc_gz_dashboard/flask/data/v1_0_0/indicator_history_item.py
sc_gz_dashboard/flask/data/v1_0_0/indicator_history_list.py
sc_gz_dashboard/flask/data/v1_0_0/indicator_item_filter.py
sc_gz_dashboard/flask/data/v1_0_0/indicator_item_list.py
sc_gz_dashboard/tests/__init__.py
sc_gz_dashboard/tests/utils_test.py
sc_gz_dashboard/tests/flask/__init__.py
sc_gz_dashboard/tests/flask/data/__init__.py
sc_gz_dashboard/tests/flask/data/v1_0_0/__init__.py
sc_gz_dashboard/tests/flask/data/v1_0_0/dashboard_data_view_test.py
sc_gz_dashboard/tests/sample_config/production.yml
sc_gz_dashboard-0.0.14.dist-info/LICENSE
sc_gz_dashboard-0.0.14.dist-info/METADATA
sc_gz_dashboard-0.0.14.dist-info/WHEEL
sc_gz_dashboard-0.0.14.dist-info/entry_points.txt
sc_gz_dashboard-0.0.14.dist-info/top_level.txt
sc_gz_dashboard-0.0.14.dist-info/RECORD
