Metadata-Version: 2.1
Name: sc-gz-dashboard
Version: 0.0.14
Summary: python dashboard
Home-page: https://github.com/Scott-Lau/sc-gz-dashboard
Author: Scott Lau
Author-email: exceedego@126.com
License: MIT
Keywords: python dashboard
Platform: POSIX
Classifier: Programming Language :: Python :: 3
Classifier: Programming Language :: Python :: 3.6
Classifier: Programming Language :: Python :: 3.7
Classifier: Programming Language :: Python :: 3.8
Classifier: Programming Language :: Python :: 3.9
Classifier: License :: OSI Approved :: MIT License
Classifier: Operating System :: OS Independent
Classifier: Topic :: Software Development
Classifier: Topic :: Utilities
Requires-Python: >=3.6
License-File: LICENSE
Requires-Dist: sc-utilities (>=0.0.7)
Requires-Dist: sc-config (>=0.0.8)
Requires-Dist: gevent (>=21.8.0)
Requires-Dist: Flask (>=2.0.1)
Requires-Dist: sc-mysqlhelper (>=0.1.4)
Requires-Dist: flask-restful (>=0.3.9)
Requires-Dist: pandas (>=1.3.2)
